opensearch/__init__.py
opensearch/protobufs/__init__.py
opensearch/protobufs/schemas/__init__.py
opensearch/protobufs/schemas/common_pb2.py
opensearch/protobufs/schemas/common_pb2.pyi
opensearch/protobufs/services/__init__.py
opensearch/protobufs/services/document_service_pb2.py
opensearch/protobufs/services/document_service_pb2.pyi
opensearch/protobufs/services/document_service_pb2_grpc.py
opensearch/protobufs/services/search_service_pb2.py
opensearch/protobufs/services/search_service_pb2.pyi
opensearch/protobufs/services/search_service_pb2_grpc.py
opensearch_protobufs-1.1.0.dist-info/LICENSE.txt
opensearch_protobufs-1.1.0.dist-info/METADATA
opensearch_protobufs-1.1.0.dist-info/RECORD
opensearch_protobufs-1.1.0.dist-info/WHEEL
