Metadata-Version: 2.1
Name: opensearch-protobufs
Author: OpenSearch Team
Home-page: https://opensearch.org/
License: Apache-2.0
Project-URL: Bug Tracker, https://github.com/opensearch-project/opensearch-protobufs/issues
Project-URL: Documentation, https://github.com/opensearch-project/opensearch-protobufs/blob/main/README.md
Project-URL: Source Code, https://github.com/opensearch-project/opensearch-protobufs
Classifier: Intended Audience :: Developers
Classifier: License :: OSI Approved :: Apache Software License
Classifier: Programming Language :: Python :: 3
Requires-Python: >=3.10
Requires-Dist: protobuf>=3.25.8
Requires-Dist: grpcio>=1.70.0
Version: 1.1.0
